beedb
