Metadata-Version: 1.1
Name: BeeDB
Version: 1.8
Summary: BeeDB it is an easier way to make a simple database
Home-page: UNKNOWN
Author: Zaid Ali
Author-email: realarty69@gmail.com
License: MIT
Keywords: db,database,json
Platform: UNKNOWN
Classifier: Development Status :: 1 - Planning
Classifier: Intended Audience :: Developers
Classifier: Programming Language :: Python :: 3
Classifier: Operating System :: Unix
Classifier: Operating System :: MacOS :: MacOS X
Classifier: Operating System :: Microsoft :: Windows
